styx_emulator-0.1.0.dist-info/METADATA
styx_emulator-0.1.0.dist-info/WHEEL
styx_emulator-0.1.0.dist-info/license_files/LICENSE.txt
styx_emulator/__init__.py
styx_emulator/_lowlevel.cpython-38-x86_64-linux-gnu.so
styx_emulator-0.1.0.dist-info/RECORD
