Metadata-Version: 2.3
Name: styx-emulator
Version: 0.1.0
License-File: LICENSE.txt
Summary: styx-emulator bindings in python
Author-email: lockbox <lockbox@struct.foo>
License: BSD-2-Clause
Requires-Python: >=3.8
